{
	"name": "PL_CDC_SAP_CDS",
	"properties": {
		"activities": [
			{
				"name": "Execute DataFlow",
				"type": "ExecuteDataFlow",
				"dependsOn": [],
				"policy": {
					"timeout": "0.12:00:00",
					"retry": 0,
					"retryIntervalInSeconds": 30,
					"secureOutput": false,
					"secureInput": false
				},
				"userProperties": [],
				"typeProperties": {
					"dataflow": {
						"referenceName": "df_sap_cdc",
						"type": "DataFlowReference",
						"parameters": {
							"KeyFields": {
								"value": "@pipeline().parameters.KeyFields",
								"type": "Expression"
							}
						},
						"datasetParameters": {
							"source1": {
								"CDS": {
									"value": "@pipeline().parameters.CDS",
									"type": "Expression"
								},
								"system_number": {
									"value": "@pipeline().globalParameters.sap_systemnumber",
									"type": "Expression"
								},
								"client_id": {
									"value": "@pipeline().globalParameters.sap_clientid",
									"type": "Expression"
								},
								"server_name": {
									"value": "@pipeline().globalParameters.sap_servername",
									"type": "Expression"
								},
								"language": {
									"value": "@pipeline().globalParameters.sap_language",
									"type": "Expression"
								},
								"user_name": {
									"value": "@pipeline().globalParameters.sap_username",
									"type": "Expression"
								}
							},
							"sink1": {
								"EnvStorage": {
									"value": "@pipeline().parameters.EnvStorage",
									"type": "Expression"
								},
								"Zone": {
									"value": "@pipeline().parameters.Zone",
									"type": "Expression"
								},
								"DataSource": {
									"value": "@pipeline().parameters.DataSource",
									"type": "Expression"
								},
								"EnvRegSys": {
									"value": "@pipeline().parameters.EnvRegSys",
									"type": "Expression"
								},
								"Domain": {
									"value": "@pipeline().parameters.Domain",
									"type": "Expression"
								},
								"Object": {
									"value": "@pipeline().parameters.Object",
									"type": "Expression"
								},
								"CDS": {
									"value": "@pipeline().parameters.CDS",
									"type": "Expression"
								}
							}
						}
					},
					"staging": {
						"linkedService": {
							"referenceName": "AzureBlobStorage1",
							"type": "LinkedServiceReference"
						},
						"folderPath": "dev/Staging/cdc"
					},
					"compute": {
						"coreCount": 8,
						"computeType": "General"
					},
					"traceLevel": "Fine",
					"continuationSettings": {
						"customizedCheckpointKey": "9e64901c-bb64-4acb-90c7-8227ae9d46e9"
					}
				}
			}
		],
		"parameters": {
			"EnvStorage": {
				"type": "string"
			},
			"Zone": {
				"type": "string"
			},
			"DataSource": {
				"type": "string"
			},
			"EnvRegSys": {
				"type": "string"
			},
			"Domain": {
				"type": "string"
			},
			"Object": {
				"type": "string"
			},
			"CDS": {
				"type": "string"
			},
			"KeyFields": {
				"type": "array"
			}
		},
		"folder": {
			"name": "Template"
		},
		"annotations": []
	}
}